cotea/__init__.py
cotea/ansible_execution_sync.py
cotea/ansible_execution_tree.py
cotea/arguments_maker.py
cotea/consts.py
cotea/cotea_config.py
cotea/debug_utils.py
cotea/progress_bar.py
cotea/runner.py
cotea/task_result.py
cotea/utils.py
cotea/wrappers/__init__.py
cotea/wrappers/ansi_breakpoint.py
cotea/wrappers/get_next_task_wrapper.py
cotea/wrappers/iterator_add_task_wrapper.py
cotea/wrappers/pbcli_run_wrapper.py
cotea/wrappers/play_prereqs_wrapper.py
cotea/wrappers/playbook_executor_wrapper.py
cotea/wrappers/strategy_run_wrapper.py
cotea/wrappers/update_active_conn_wrapper.py
cotea/wrappers/wrapper_base.py
cotea-1.3.20.dist-info/LICENSE.md
cotea-1.3.20.dist-info/METADATA
cotea-1.3.20.dist-info/WHEEL
cotea-1.3.20.dist-info/top_level.txt
cotea-1.3.20.dist-info/RECORD
