Metadata-Version: 2.1
Name: cotea
Version: 1.3.20
Summary: Tool that provides Python API to run Ansible programmatically.
Home-page: https://github.com/ispras/cotea
Author: David Badalyan
Author-email: dbadalyan@ispras.ru
Project-URL: Bug Tracker, https://github.com/ispras/cotea/issues
Classifier: Programming Language :: Python :: 3
Classifier: License :: OSI Approved :: Apache Software License
Classifier: Operating System :: OS Independent
Requires-Python: >=3.8
License-File: LICENSE.md
Requires-Dist: ansible-core ~=2.9
